Metadata-Version: 2.1
Name: wdf-pypack
Version: 0.0.3
Summary: Python Package for modules of WDF
Home-page: https://github.com/
Author: LinYanzhou
Author-email: yanzhou.lin@wondfo.com.cn
License: UNKNOWN
Platform: UNKNOWN
Classifier: Programming Language :: Python :: 3
Classifier: License :: OSI Approved :: MIT License
Classifier: Operating System :: OS Independent
